<?xml version="1.0" encoding="UTF-8"?>
<Ui xmlns="http://www.blizzard.com/wow/ui/">
   <Script file="Elements\Bar1.lua" />
   <Script file="Elements\Bar2.lua" />
   <Script file="Elements\Bar3.lua" />
   <Script file="Elements\Bar4.lua" />
   <Script file="Elements\Bar5.lua" />
   <Script file="Elements\CustomBar.lua" />
   <Script file="Elements\Stancebar.lua" />
   <Script file="Elements\Petbar.lua" />
   <Script file="Elements\Extrabar.lua" />
   <Script file="Elements\Vehicle.lua" />
   <Script file="Elements\BlizzArt.lua" />
   <Script file="Elements\Fader.lua" />

   <Script file="ButtonRange.lua" />
   <Script file="Keybind.lua" />
   <Script file="ButtonStyle.lua" />
   <Script file="Cooldowns.lua" />
   <Script file="MicroMenu.lua" />

   <Script file="Elements\ExtraQuestButton.lua" />
</Ui>